{
  "stateSlug": "alabama",
  "stateName": "Alabama",
  "citySlug": "birmingham-business-loans",
  "cityName": "Birmingham",
  "industrySlug": "restaurant-loans",
  "industryLabel": "Restaurant & Food Service",
  "title": "Birmingham Restaurant Business Loans | Alabama",
  "description": "Compare restaurant business loans, working capital and equipment financing available in Birmingham, Alabama.",
  "h1": "Birmingham Restaurant Business Loans",
  "intro": "Access working capital, credit lines and equipment financing designed for restaurant businesses in Birmingham, Alabama.",
  "schema": {
    "@context": "https://schema.org",
    "@type": "FinancialService",
    "name": "Birmingham Restaurant Business Loans",
    "areaServed": "Birmingham, Alabama",
    "serviceType": "Working Capital, Business Line of Credit, Equipment Financing",
    "provider": {
      "@type": "Organization",
      "name": "Small Business Capital"
    },
    "category": "Restaurant & Food Service"
  }
}