{
  "stateSlug": "arizona",
  "stateName": "Arizona",
  "citySlug": "tucson-business-loans",
  "cityName": "Tucson",
  "industrySlug": "construction-loans",
  "industryLabel": "Construction & Trades",
  "title": "Tucson Construction Business Loans | Arizona",
  "description": "Compare construction business loans, working capital and equipment financing available in Tucson, Arizona.",
  "h1": "Tucson Construction Business Loans",
  "intro": "Access working capital, credit lines and equipment financing designed for construction businesses in Tucson, Arizona.",
  "schema": {
    "@context": "https://schema.org",
    "@type": "FinancialService",
    "name": "Tucson Construction Business Loans",
    "areaServed": "Tucson, Arizona",
    "serviceType": "Working Capital, Business Line of Credit, Equipment Financing",
    "provider": {
      "@type": "Organization",
      "name": "Small Business Capital"
    },
    "category": "Construction & Trades"
  }
}