{
  "stateSlug": "georgia",
  "stateName": "Georgia",
  "citySlug": "macon-business-loans",
  "cityName": "Macon",
  "industrySlug": "trucking-loans",
  "industryLabel": "Trucking & Logistics",
  "title": "Macon Trucking Business Loans | Georgia",
  "description": "Compare trucking business loans, working capital and equipment financing available in Macon, Georgia.",
  "h1": "Macon Trucking Business Loans",
  "intro": "Access working capital, credit lines and equipment financing designed for trucking businesses in Macon, Georgia.",
  "schema": {
    "@context": "https://schema.org",
    "@type": "FinancialService",
    "name": "Macon Trucking Business Loans",
    "areaServed": "Macon, Georgia",
    "serviceType": "Working Capital, Business Line of Credit, Equipment Financing",
    "provider": {
      "@type": "Organization",
      "name": "Small Business Capital"
    },
    "category": "Trucking & Logistics"
  }
}