{
  "stateSlug": "illinois",
  "stateName": "Illinois",
  "citySlug": "joliet-business-loans",
  "cityName": "Joliet",
  "industrySlug": "construction-loans",
  "industryLabel": "Construction & Trades",
  "title": "Joliet Construction Business Loans | Illinois",
  "description": "Compare construction business loans, working capital and equipment financing available in Joliet, Illinois.",
  "h1": "Joliet Construction Business Loans",
  "intro": "Access working capital, credit lines and equipment financing designed for construction businesses in Joliet, Illinois.",
  "schema": {
    "@context": "https://schema.org",
    "@type": "FinancialService",
    "name": "Joliet Construction Business Loans",
    "areaServed": "Joliet, Illinois",
    "serviceType": "Working Capital, Business Line of Credit, Equipment Financing",
    "provider": {
      "@type": "Organization",
      "name": "Small Business Capital"
    },
    "category": "Construction & Trades"
  }
}