{
  "stateSlug": "illinois",
  "stateName": "Illinois",
  "citySlug": "chicago-business-loans",
  "cityName": "Chicago",
  "industrySlug": "trucking-loans",
  "industryLabel": "Trucking & Logistics",
  "title": "Chicago Trucking Business Loans | Illinois",
  "description": "Compare trucking business loans, working capital and equipment financing available in Chicago, Illinois.",
  "h1": "Chicago Trucking Business Loans",
  "intro": "Access working capital, credit lines and equipment financing designed for trucking businesses in Chicago, Illinois.",
  "schema": {
    "@context": "https://schema.org",
    "@type": "FinancialService",
    "name": "Chicago Trucking Business Loans",
    "areaServed": "Chicago, Illinois",
    "serviceType": "Working Capital, Business Line of Credit, Equipment Financing",
    "provider": {
      "@type": "Organization",
      "name": "Small Business Capital"
    },
    "category": "Trucking & Logistics"
  }
}