{
  "stateSlug": "pennsylvania",
  "stateName": "Pennsylvania",
  "citySlug": "philadelphia-business-loans",
  "cityName": "Philadelphia",
  "industrySlug": "trucking-loans",
  "industryLabel": "Trucking & Logistics",
  "title": "Philadelphia Trucking Business Loans | Pennsylvania",
  "description": "Compare trucking business loans, working capital and equipment financing available in Philadelphia, Pennsylvania.",
  "h1": "Philadelphia Trucking Business Loans",
  "intro": "Access working capital, credit lines and equipment financing designed for trucking businesses in Philadelphia, Pennsylvania.",
  "schema": {
    "@context": "https://schema.org",
    "@type": "FinancialService",
    "name": "Philadelphia Trucking Business Loans",
    "areaServed": "Philadelphia, Pennsylvania",
    "serviceType": "Working Capital, Business Line of Credit, Equipment Financing",
    "provider": {
      "@type": "Organization",
      "name": "Small Business Capital"
    },
    "category": "Trucking & Logistics"
  }
}