{
  "stateSlug": "wisconsin",
  "stateName": "Wisconsin",
  "citySlug": "milwaukee-business-loans",
  "cityName": "Milwaukee",
  "industrySlug": "trucking-loans",
  "industryLabel": "Trucking & Logistics",
  "title": "Milwaukee Trucking Business Loans | Wisconsin",
  "description": "Compare trucking business loans, working capital and equipment financing available in Milwaukee, Wisconsin.",
  "h1": "Milwaukee Trucking Business Loans",
  "intro": "Access working capital, credit lines and equipment financing designed for trucking businesses in Milwaukee, Wisconsin.",
  "schema": {
    "@context": "https://schema.org",
    "@type": "FinancialService",
    "name": "Milwaukee Trucking Business Loans",
    "areaServed": "Milwaukee, Wisconsin",
    "serviceType": "Working Capital, Business Line of Credit, Equipment Financing",
    "provider": {
      "@type": "Organization",
      "name": "Small Business Capital"
    },
    "category": "Trucking & Logistics"
  }
}